interactive_input/__init__.py
interactive_input/input.py
interactive_input/subwindow.py
interactive_input/test.py
interactive_input/window.py
interactive_input-0.6.1.dist-info/LICENSE
interactive_input-0.6.1.dist-info/METADATA
interactive_input-0.6.1.dist-info/WHEEL
interactive_input-0.6.1.dist-info/top_level.txt
interactive_input-0.6.1.dist-info/RECORD
