Metadata-Version: 2.1
Name: interactive-input
Version: 0.6.1
Summary: curses based interactive value input
Home-page: https://github.com/0Delta/py-interactive_input
Author: 0Delta
Author-email: 0deltast@gmail.com
License: MIT
Keywords: interactive_input 0Delta
Platform: UNKNOWN
Classifier: License :: OSI Approved :: MIT License
Classifier: Programming Language :: Python :: 3.6
Classifier: Development Status :: 3 - Alpha
Classifier: Environment :: Console :: Curses
Requires-Python: >=3.6
